LICENSE
MANIFEST.in
README.md
requirements.txt
setup.py
musco/__init__.py
musco/tf/__init__.py
musco/tf/compressor/__init__.py
musco/tf/compressor/compress.py
musco/tf/compressor/common/__init__.py
musco/tf/compressor/common/utils.py
musco/tf/compressor/decompositions/__init__.py
musco/tf/compressor/decompositions/constructor.py
musco/tf/compressor/decompositions/cp3.py
musco/tf/compressor/decompositions/cp4.py
musco/tf/compressor/decompositions/cpd.py
musco/tf/compressor/decompositions/svd.py
musco/tf/compressor/decompositions/tucker2.py
musco/tf/compressor/exceptions/__init__.py
musco/tf/compressor/exceptions/compression_error.py
musco/tf/compressor/layers/__init__.py
musco/tf/compressor/layers/group_conv_2d.py
musco/tf/compressor/layers/svd_layer.py
musco/tf/compressor/rank_selection/__init__.py
musco/tf/compressor/rank_selection/estimator.py
musco/tf/compressor/rank_selection/vbmf.py
musco/tf/optimizer/__init__.py
musco/tf/optimizer/trt.py
musco_tf.egg-info/PKG-INFO
musco_tf.egg-info/SOURCES.txt
musco_tf.egg-info/dependency_links.txt
musco_tf.egg-info/requires.txt
musco_tf.egg-info/top_level.txt